barangay/__init__.py
barangay/data.py
barangay/fuzz.py
barangay/models.py
barangay/search.py
barangay/utils.py
barangay/data/barangay.json
barangay/data/barangay.yaml
barangay/data/barangay_extended.json
barangay/data/barangay_extended.yaml
barangay/data/barangay_flat.json
barangay/data/barangay_flat.yaml
barangay/data/fuzzer_base.parquet
barangay/data/2025-07-08/barangay.json
barangay/data/2025-07-08/barangay.yaml
barangay/data/2025-07-08/barangay_extended.json
barangay/data/2025-07-08/barangay_extended.yaml
barangay/data/2025-07-08/barangay_flat.json
barangay/data/2025-07-08/barangay_flat.yaml
barangay/data/2025-07-08/fuzzer_base.parquet
barangay/data/2025-08-29/barangay.json
barangay/data/2025-08-29/barangay.yaml
barangay/data/2025-08-29/barangay_extended.json
barangay/data/2025-08-29/barangay_extended.yaml
barangay/data/2025-08-29/barangay_flat.json
barangay/data/2025-08-29/barangay_flat.yaml
barangay/data/2025-08-29/fuzzer_base.parquet
barangay/data/2025-10-13/barangay.json
barangay/data/2025-10-13/barangay.yaml
barangay/data/2025-10-13/barangay_extended.json
barangay/data/2025-10-13/barangay_extended.yaml
barangay/data/2025-10-13/barangay_flat.json
barangay/data/2025-10-13/barangay_flat.yaml
barangay-2026.1.13.0.dist-info/METADATA
barangay-2026.1.13.0.dist-info/WHEEL
barangay-2026.1.13.0.dist-info/licenses/LICENSE
barangay-2026.1.13.0.dist-info/RECORD
