Metadata-Version: 2.4
Name: barangay
Version: 2026.1.13.0
Summary: Philippines Standard Geographic Code (PSGC) 2026 Python package, Fuzzy Search, JSON, and YAML.
Project-URL: homepage, https://hawitsu.xyz
Project-URL: repository, https://github.com/bendlikeabamboo/barangay
Project-URL: documentation, https://github.com/bendlikeabamboo/barangay/blob/main/README.md
Project-URL: Bug Tracker, https://github.com/bendlikeabamboo/barangay/issues
Author-email: bendlikeabamboo <manuelb@hawitsu.xyz>
License: MIT
License-File: LICENSE
Keywords: barangay,geography,philippines,region
Classifier: Intended Audience :: Science/Research
Classifier: Topic :: Scientific/Engineering :: GIS
Classifier: Topic :: Scientific/Engineering :: Information Analysis
Requires-Python: >=3.10
Requires-Dist: fastparquet<2025.0.0,>=2024.11.0
Requires-Dist: pandas<3.0.0,>=2.3.2
Requires-Dist: pydantic<3.0.0,>=2.11.7
Requires-Dist: rapidfuzz<4.0.0,>=3.14.0
